jsondataclasses/__init__.py
jsondataclasses-0.0.6.dist-info/LICENSE
jsondataclasses-0.0.6.dist-info/METADATA
jsondataclasses-0.0.6.dist-info/WHEEL
jsondataclasses-0.0.6.dist-info/top_level.txt
jsondataclasses-0.0.6.dist-info/RECORD
