Metadata-Version: 2.1
Name: jsondataclasses
Version: 0.0.6
Summary: Typed JSON dataclasses
Home-page: https://github.com/issy/python-jsondataclasses
License: MIT
Classifier: License :: OSI Approved :: MIT License
Requires-Python: >=3.9.0
License-File: LICENSE
